{
  "_id": "7a15cbf59bc9b3796d4667912e89871c8debe7c0f4e42956448ba3faff9aa196",
  "feed": "market-watch",
  "title": "Walmart will phase out quarterly bonuses for store workers",
  "text": "<p>Walmart said it would scrap the benefit, dubbed “MyShare,” at the end of the company's fiscal year on Jan. 31, 2022, according to a memo sent to staff discussing coming wage increases. “We are rolling MyShare into associates' base pay going forward,” the memo said.</p><p>A Walmart spokeswoman said most workers say their hourly wage is the most important part of their pay, and that folding the bonus into wages increases the amount of consistent, predictable income. She said the quarterly bonus makes up just a portion of the pay increase workers are receiving.</p><p>The bonuses have been part of Walmart store workers' potential compensation for decades. Early on, Walmart distributed the bonuses annually based on store performance. Over the years the retailer has used a variety of metrics, including attendance or store-theft level, to determine the payout. Walmart moved the bonus to a quarterly structure in 2007. In some quarters, a store's performance doesn't qualify workers for a bonus.</p><p>An expanded version of this article appears on WSJ.com.</p><p>Popular stories from WSJ.com:</p><p>How TikTok Serves Up Sex and Drug Videos to Minors</p><p>As a Delta Wave Peaks in Some States, Others Brace for What's Next</p><p>On 9/11, Split-Second Decisions by Employees at ICAP Affected the Rest of Their Lives</p>",
  "published": "2021-09-09T10:12:00.000Z",
  "tags": [
    {
      "id": "US9311421039",
      "nexusId": "10042309",
      "name": "Walmart Inc.",
      "offsets": [
        {
          "start": 854,
          "end": 861
        },
        {
          "start": 0,
          "end": 7
        },
        {
          "start": 589,
          "end": 596
        },
        {
          "start": 658,
          "end": 665
        },
        {
          "start": 268,
          "end": 275
        }
      ]
    }
  ]
}