{
  "_id": "03bc89ab4d8dc4c4d380947b4ba1924938fe6cd242c1297d904100a475c8b9a1",
  "feed": "market-watch",
  "title": "The S&P 500 beat both Dow, and Nasdaq in 2021 by the widest margin in 24 years. Here's what history says happens in 2022.",
  "text": "<p>Tesla smashes quarterly delivery record, sees sales surge 87% in 2021</p><p>Tesla Inc. delivered more than 308,000 vehicles in the fourth quarter, blowing away expectations, and saw sales surge about 87% in a year that saw it top $1 trillion in market cap for the first time. See full story.</p><p>Wall Street analysts' favorite stocks for 2022 include Alaska Air, Caesars and Lithia Motors</p><p>General Motors, Salesforce and PayPal are among the 20 S&amp;P 500 stocks that analysts both heavily favor and expect to rise to the most. See full story.</p><p>A New Year's resolution for retirees</p><p>How frequently should you be checking your portfolio? See full story.</p><p>These are tech's 10 megatrends for 2022 — and the stocks to buy</p><p>From cloud computing to autonomous vehicles to 5G, here's what to watch. See full story.</p><p>MARKETWATCH PERSONAL FINANCE</p><p>Affordability has dropped to the lowest level since 2008 nationwide, amid rising interest rates and home prices. See full story.</p>",
  "published": "2022-01-02T17:00:05.000Z",
  "tags": [
    {
      "id": "US79466L3024",
      "nexusId": "10009678",
      "name": "Salesforce, Inc.",
      "offsets": [
        {
          "start": 395,
          "end": 405
        }
      ]
    }
  ]
}