{
  "_id": "556cf3c8833df18011780e5b72b40d61cf488ddb7ce7dd2b988be6c04e18f1bb",
  "feed": "wall-street-journal",
  "title": "Business & Finance",
  "text": "<p>U.S. household spending bounced back in June, but the upswing in Covid-19 cases related to the Delta variant is injecting uncertainty into the economic outlook.</p><p>---</p><p>Big oil companies are raking in their highest profits since the onset of the pandemic, but they plan to continue spending sparingly to boost production.</p><p>---</p><p>Robinhood's bid to revolutionize IPOs has created losses for investors instead, after the company's highly anticipated listing fell flat.</p><p>---</p><p>U.S. stocks fell, but the S&amp;P 500, Dow and Nasdaq all posted gains for July.</p><p>---</p><p>Procter &amp; Gamble gave a somber outlook for the year ahead, predicting slower sales and higher costs.</p><p>---</p><p>Amazon was fined about $887 million by an EU privacy regulator for violations related to its advertising.</p><p>---</p><p>Music publisher Primary Wave has acquired the largest stake in the estate of the late pop star Prince.</p>",
  "published": "2021-07-31T00:00:00.000Z",
  "tags": [
    {
      "id": "US7427181091",
      "nexusId": "10044575",
      "name": "The Procter & Gamble Company",
      "offsets": [
        {
          "start": 545,
          "end": 561
        }
      ]
    }
  ]
}