{
  "_id": "658e1688c80441f18b0111250f944602baea82a21552d7a26a3a150c958608b6",
  "feed": "ftcomall",
  "title": "Letter: Spurning the FT Lunch's usual bevvy gets my vote",
  "text": "<p>James Anderson may have offended purists such as Nicola Ricolfi in his choice of <em>fritto misto</em> rather than the “more appropriate” tagliatelle for his Lunch with the FT (<a href=\"https://www.ft.com/content/7a5d123e-0c92-45f5-a6ec-5f3cca022807\">Letters</a>, April 23) but at least he didn't choose to accompany it with the vile Diet Coke, the preferred beverage of so many FT Lunchers.</p> <p><strong>Sally Turff<br></strong><em>King's Lynn, Norfolk, UK</em> </p><p>Source:  2022 'Letter: Spurning the FT Lunch's usual bevvy gets my vote' FT.com 29 April. Used under licence from the Financial Times. © The Financial Times Limited 2022. All Rights Reserved. </p><p>Please do not cut and paste FT articles and redistribute by email or post to the web.</p>",
  "published": "2022-04-29T20:32:17.773Z",
  "tags": [
    {
      "id": "US1912161007",
      "nexusId": "10017668",
      "name": "The Coca-Cola Company",
      "offsets": [
        {
          "start": 252,
          "end": 256
        }
      ]
    }
  ]
}