{
  "_id": "41aeea154cf44e31b9419561706cf56499b604c20d8b6eda668ff9c5b1cb69cc",
  "feed": "market-watch",
  "title": "Small fire breaks out near Disney's Cinderella Castle at Magic Kingdom",
  "text": "<p>Cinderella Castle and surrounding areas were evacuated as firefighters put out the fire.</p><p>One person suffered minor injuries and was treated at the scene after accidentally inhaling chemicals from a fire extinguisher, fire officials said.</p><p>Uncredited</p>",
  "published": "2021-12-15T05:22:00.000Z",
  "tags": [
    {
      "id": "US2546871060",
      "name": "The Walt Disney Company",
      "offsets": [
        {
          "start": 27,
          "end": 33
        }
      ],
      "nexusId": "10078857"
    }
  ]
}